Workbook

Sheet Інструкція
A1: Product Hunter — модель відбору товарів (v1, 01.10.2026)
A3: Як користуватись
A4: 1. «Параметри»: змініть сині значення в жовтих клітинках (маржа, апрув, викуп, курс). Решта аркушів перерахується автоматично.
A5: 2. «Економіка»: допустима ціна ліда (беззбиток і ціль) + таблиця чутливості.
A6: 3. «Бенчмарки»: ваші реальні товари з Meta за 90 днів і їхній орієнтовний прибуток при поточних параметрах.
A7: 4. «Ваги»: вага кожного блоку Score і шкала оцінювання 0–5. Ваги можна міняти (сума має бути 100).
A8: 5. «Скоринг»: додавайте нові товари в порожні рядки, ставте оцінки 0–5 і очікуваний CPL. Score і рішення рахуються самі.
A9: 6. «Протокол тесту»: правила запуску, зупинки і масштабування з конкретними цифрами.
A11: Кольори
A12: Синій текст — ручні вхідні дані. Чорний — формули. Зелений — посилання на інший аркуш. Жовта заливка — ключові припущення, які варто перевірити.
A14: Важливо
A15: • Оцінки 0–5 у «Скоринг» для нових товарів — первинні експертні оцінки з пілоту, а не результат автоматичного збору даних.
... A17: • Бенчмарки охоплюють кампанії з трьох найбільших кабінетів (1 бм 2 рк (MAX), ХітМаркет, рк2), топ-20 кампаній кожного за спендом.

Sheet Параметри
A1: Параметри економіки
A3: Параметр | B3: Значення | C3: Джерело / примітка
A4: Маржа з товару (продаж − закупка), ₴ | B4: 300 | C4: Від користувача: 250–350 ₴, взято середнє
A5: Маржа з допродажів у середньому, ₴ | B5: 250 | C5: Від користувача: 200–300 ₴, взято середнє
A6: Апрув (підтверджені / ліди) | B6: 0.64 | C6: Від користувача: середнє по LP-CRM
A7: Викуп (отримані / відправлені) | B7: 0.82 | C7: Від користувача: середнє по LP-CRM
A8: Витрата на 1 невикуп (повернення посилки), ₴ | B8: 150 | C8: Від користувача: ~150 ₴
A9: Інші витрати на 1 підтверджене замовлення, ₴ | B9: 23 | C9: Від користувача: 23 ₴ за підтверджене замовлення
A10: Курс ₴ за $1 | B10: 41.5 | C10: ПРИПУЩЕННЯ: орієнтовний курс. Оновлюйте
A11: Цільова частка прибутку від беззбиткового CPL | B11: 0.4 | C11: Пропозиція: лишаємо 40 % запасу, ціль = 60 % від беззбитку
A12: Тестовий бюджет, $/день | B12: 14 | C12: З вашої практики (тести $11–15)
A13: Тривалість тесту, днів | B13: 3 | C13: Пропозиція
A14: Бюджет масштабування, $/день | B14: 50 | C14: З вашої практики (скейл $50)
A15: Мінімальний апрув для масштабування | B15: 0.6 | C15: Пропозиція
... A17: Комісія з маржі допродажів | B17: 0.23 | C17: Від користувача: 23 % з маржі допродажів

Sheet Економіка
A1: Допустима ціна ліда
A3: Показник | B3: Значення | C3: Формула / пояснення
A4: Повна маржа з викупленого замовлення, ₴ | B4: =Параметри!B4+Параметри!B5*(1-Параметри!B17) | C4: маржа товару + допродажі мінус комісія з допродажів
A5: Дохід з 1 підтвердженого замовлення, ₴ | B5: =Параметри!B7*B4-(1-Параметри!B7)*Параметри!B8-Параметри!B9 | C5: викуп × маржа − невикуп × повернення − інші витрати
A6: Беззбитковий CPL, ₴ | B6: =Параметри!B6*B5 | C6: апрув × дохід з підтвердженого
A7: Беззбитковий CPL, $ | B7: =B6/Параметри!B10 | C7: максимум, який можна платити за лід
A8: Цільовий CPL, $ | B8: =B7*(1-Параметри!B11) | C8: ціль, за якої лишається запас прибутку
A9: Ціна викупленого замовлення при цільовому CPL, $ | B9: =B8/(Параметри!B6*Параметри!B7) | C9: скільки реклами припадає на 1 викуп
A10: Прибуток з 1 ліда при цільовому CPL, ₴ | B10: =B6-B8*Параметри!B10
A13: Чутливість: беззбитковий CPL ($) залежно від апруву (рядки) і повної маржі (стовпці); викуп і повернення — з «Параметри»
A14: Апрув \ Маржа, ₴ | B14: 400 | C14: 450 | D14: 500 | E14: 550 | F14: 600 | G14: 650 | H14: 700
A15: 0.5 | B15: =$A15*(Параметри!$B$7*B$14-(1-Параметри!$B$7)*Параметри!$B$8-Параметри!$B$9)/Параметри!$B$10 | C15: =$A15*(Параметри!$B$7*C$14-(1-Параметри!$B$7)*Параметри!$B$8-Параметри!$B$9)/Параметри!$B$10 | D15: =$A15*(Параметри!$B$7*D$14-(1-Параметри!$B$7)*Параметри!$B$8-Параметри!$B$9)/Параметри!$B$10 | E15: =$A15*(Параметри!$B$7*E$14-(1-Параметри!$B$7)*Параметри!$B$8-Параметри!$B$9)/Параметри!$B$10 | F15: =$A15*(Параметри!$B$7*F$14-(1-Параметри!$B$7)*Параметри!$B$8-Параметри!$B$9)/Параметри!$B$10 | G15: =$A15*(Параметри!$B$7*G$14-(1-Параметри!$B$7)*Параметри!$B$8-Параметри!$B$9)/Параметри!$B$10 | H15: =$A15*(Параметри!$B$7*H$14-(1-Параметри!$B$7)*Параметри!$B$8-Параметри!$B$9)/Параметри!$B$10
A16: 0.55 | B16: =$A16*(Параметри!$B$7*B$14-(1-Параметри!$B$7)*Параметри!$B$8-Параметри!$B$9)/Параметри!$B$10 | C16: =$A16*(Параметри!$B$7*C$14-(1-Параметри!$B$7)*Параметри!$B$8-Параметри!$B$9)/Параметри!$B$10 | D16: =$A16*(Параметри!$B$7*D$14-(1-Параметри!$B$7)*Параметри!$B$8-Параметри!$B$9)/Параметри!$B$10 | E16: =$A16*(Параметри!$B$7*E$14-(1-Параметри!$B$7)*Параметри!$B$8-Параметри!$B$9)/Параметри!$B$10 | F16: =$A16*(Параметри!$B$7*F$14-(1-Параметри!$B$7)*Параметри!$B$8-Параметри!$B$9)/Параметри!$B$10 | G16: =$A16*(Параметри!$B$7*G$14-(1-Параметри!$B$7)*Параметри!$B$8-Параметри!$B$9)/Параметри!$B$10 | H16: =$A16*(Параметри!$B$7*H$14-(1-Параметри!$B$7)*Параметри!$B$8-Параметри!$B$9)/Параметри!$B$10
A17: 0.6 | B17: =$A17*(Параметри!$B$7*B$14-(1-Параметри!$B$7)*Параметри!$B$8-Параметри!$B$9)/Параметри!$B$10 | C17: =$A17*(Параметри!$B$7*C$14-(1-Параметри!$B$7)*Параметри!$B$8-Параметри!$B$9)/Параметри!$B$10 | D17: =$A17*(Параметри!$B$7*D$14-(1-Параметри!$B$7)*Параметри!$B$8-Параметри!$B$9)/Параметри!$B$10 | E17: =$A17*(Параметри!$B$7*E$14-(1-Параметри!$B$7)*Параметри!$B$8-Параметри!$B$9)/Параметри!$B$10 | F17: =$A17*(Параметри!$B$7*F$14-(1-Параметри!$B$7)*Параметри!$B$8-Параметри!$B$9)/Параметри!$B$10 | G17: =$A17*(Параметри!$B$7*G$14-(1-Параметри!$B$7)*Параметри!$B$8-Параметри!$B$9)/Параметри!$B$10 | H17: =$A17*(Параметри!$B$7*H$14-(1-Параметри!$B$7)*Параметри!$B$8-Параметри!$B$9)/Параметри!$B$10
A18: 0.64 | B18: =$A18*(Параметри!$B$7*B$14-(1-Параметри!$B$7)*Параметри!$B$8-Параметри!$B$9)/Параметри!$B$10 | C18: =$A18*(Параметри!$B$7*C$14-(1-Параметри!$B$7)*Параметри!$B$8-Параметри!$B$9)/Параметри!$B$10 | D18: =$A18*(Параметри!$B$7*D$14-(1-Параметри!$B$7)*Параметри!$B$8-Параметри!$B$9)/Параметри!$B$10 | E18: =$A18*(Параметри!$B$7*E$14-(1-Параметри!$B$7)*Параметри!$B$8-Параметри!$B$9)/Параметри!$B$10 | F18: =$A18*(Параметри!$B$7*F$14-(1-Параметри!$B$7)*Параметри!$B$8-Параметри!$B$9)/Параметри!$B$10 | G18: =$A18*(Параметри!$B$7*G$14-(1-Параметри!$B$7)*Параметри!$B$8-Параметри!$B$9)/Параметри!$B$10 | H18: =$A18*(Параметри!$B$7*H$14-(1-Параметри!$B$7)*Параметри!$B$8-Параметри!$B$9)/Параметри!$B$10
A19: 0.7 | B19: =$A19*(Параметри!$B$7*B$14-(1-Параметри!$B$7)*Параметри!$B$8-Параметри!$B$9)/Параметри!$B$10 | C19: =$A19*(Параметри!$B$7*C$14-(1-Параметри!$B$7)*Параметри!$B$8-Параметри!$B$9)/Параметри!$B$10 | D19: =$A19*(Параметри!$B$7*D$14-(1-Параметри!$B$7)*Параметри!$B$8-Параметри!$B$9)/Параметри!$B$10 | E19: =$A19*(Параметри!$B$7*E$14-(1-Параметри!$B$7)*Параметри!$B$8-Параметри!$B$9)/Параметри!$B$10 | F19: =$A19*(Параметри!$B$7*F$14-(1-Параметри!$B$7)*Параметри!$B$8-Параметри!$B$9)/Параметри!$B$10 | G19: =$A19*(Параметри!$B$7*G$14-(1-Параметри!$B$7)*Параметри!$B$8-Параметри!$B$9)/Параметри!$B$10 | H19: =$A19*(Параметри!$B$7*H$14-(1-Параметри!$B$7)*Параметри!$B$8-Параметри!$B$9)/Параметри!$B$10
A20: 0.75 | B20: =$A20*(Параметри!$B$7*B$14-(1-Параметри!$B$7)*Параметри!$B$8-Параметри!$B$9)/Параметри!$B$10 | C20: =$A20*(Параметри!$B$7*C$14-(1-Параметри!$B$7)*Параметри!$B$8-Параметри!$B$9)/Параметри!$B$10 | D20: =$A20*(Параметри!$B$7*D$14-(1-Параметри!$B$7)*Параметри!$B$8-Параметри!$B$9)/Параметри!$B$10 | E20: =$A20*(Параметри!$B$7*E$14-(1-Параметри!$B$7)*Параметри!$B$8-Параметри!$B$9)/Параметри!$B$10 | F20: =$A20*(Параметри!$B$7*F$14-(1-Параметри!$B$7)*Параметри!$B$8-Параметри!$B$9)/Параметри!$B$10 | G20: =$A20*(Параметри!$B$7*G$14-(1-Параметри!$B$7)*Параметри!$B$8-Параметри!$B$9)/Параметри!$B$10 | H20: =$A20*(Параметри!$B$7*H$14-(1-Параметри!$B$7)*Параметри!$B$8-Параметри!$B$9)/Параметри!$B$10

Sheet Бенчмарки
A1: Ваші товари: факт Meta за 90 днів (до 01.10.2026) і орієнтовний прибуток
A3: Товар | B3: ID | C3: Спенд, $ | D3: Ліди | E3: CPL, $ | F3: Прибуток з 1 ліда, ₴ | G3: Прибуток за 90 днів, ₴ | H3: ROMI | I3: Статус
A4: Подрібнювач | B4: id72 | C4: 11991.55 | D4: 5462 | E4: =IFERROR(C4/D4,0) | F4: =Економіка!$B$6-E4*Параметри!$B$10 | G4: =F4*D4 | H4: =IFERROR(G4/(C4*Параметри!$B$10),0) | I4: =IF(E4<=Економіка!$B$8,"✅ прибутковий",IF(E4<=Економіка!$B$7,"⚠️ тонка маржа","❌ збиток"))
A5: Блендер | B5: id260 | C5: 966.6 | D5: 404 | E5: =IFERROR(C5/D5,0) | F5: =Економіка!$B$6-E5*Параметри!$B$10 | G5: =F5*D5 | H5: =IFERROR(G5/(C5*Параметри!$B$10),0) | I5: =IF(E5<=Економіка!$B$8,"✅ прибутковий",IF(E5<=Економіка!$B$7,"⚠️ тонка маржа","❌ збиток"))
A6: Компресор | B6: id51 | C6: 810.44 | D6: 298 | E6: =IFERROR(C6/D6,0) | F6: =Економіка!$B$6-E6*Параметри!$B$10 | G6: =F6*D6 | H6: =IFERROR(G6/(C6*Параметри!$B$10),0) | I6: =IF(E6<=Економіка!$B$8,"✅ прибутковий",IF(E6<=Економіка!$B$7,"⚠️ тонка маржа","❌ збиток"))
A7: Сушарка кругла | B7: id263 | C7: 633.7 | D7: 211 | E7: =IFERROR(C7/D7,0) | F7: =Економіка!$B$6-E7*Параметри!$B$10 | G7: =F7*D7 | H7: =IFERROR(G7/(C7*Параметри!$B$10),0) | I7: =IF(E7<=Економіка!$B$8,"✅ прибутковий",IF(E7<=Економіка!$B$7,"⚠️ тонка маржа","❌ збиток"))
A8: Сушарка | B8: id255 | C8: 338.66 | D8: 116 | E8: =IFERROR(C8/D8,0) | F8: =Економіка!$B$6-E8*Параметри!$B$10 | G8: =F8*D8 | H8: =IFERROR(G8/(C8*Параметри!$B$10),0) | I8: =IF(E8<=Економіка!$B$8,"✅ прибутковий",IF(E8<=Економіка!$B$7,"⚠️ тонка маржа","❌ збиток"))
A9: Кавоварка | B9: id117 | C9: 744.39 | D9: 221 | E9: =IFERROR(C9/D9,0) | F9: =Економіка!$B$6-E9*Параметри!$B$10 | G9: =F9*D9 | H9: =IFERROR(G9/(C9*Параметри!$B$10),0) | I9: =IF(E9<=Економіка!$B$8,"✅ прибутковий",IF(E9<=Економіка!$B$7,"⚠️ тонка маржа","❌ збиток"))
A10: Аерогриль | B10: id20/155 | C10: 2009.37 | D10: 532 | E10: =IFERROR(C10/D10,0) | F10: =Економіка!$B$6-E10*Параметри!$B$10 | G10: =F10*D10 | H10: =IFERROR(G10/(C10*Параметри!$B$10),0) | I10: =IF(E10<=Економіка!$B$8,"✅ прибутковий",IF(E10<=Економіка!$B$7,"⚠️ тонка маржа","❌ збиток"))
A11: Віброплатформа | B11: id75 | C11: 2281.9 | D11: 675 | E11: =IFERROR(C11/D11,0) | F11: =Економіка!$B$6-E11*Параметри!$B$10 | G11: =F11*D11 | H11: =IFERROR(G11/(C11*Параметри!$B$10),0) | I11: =IF(E11<=Економіка!$B$8,"✅ прибутковий",IF(E11<=Економіка!$B$7,"⚠️ тонка маржа","❌ збиток"))
A12: Рюкзак | B12: id42 | C12: 263.97 | D12: 75 | E12: =IFERROR(C12/D12,0) | F12: =Економіка!$B$6-E12*Параметри!$B$10 | G12: =F12*D12 | H12: =IFERROR(G12/(C12*Параметри!$B$10),0) | I12: =IF(E12<=Економіка!$B$8,"✅ прибутковий",IF(E12<=Економіка!$B$7,"⚠️ тонка маржа","❌ збиток"))
A13: Аплікатор Кузнєцова | B13: id144 | C13: 155.09 | D13: 48 | E13: =IFERROR(C13/D13,0) | F13: =Економіка!$B$6-E13*Параметри!$B$10 | G13: =F13*D13 | H13: =IFERROR(G13/(C13*Параметри!$B$10),0) | I13: =IF(E13<=Економіка!$B$8,"✅ прибутковий",IF(E13<=Економіка!$B$7,"⚠️ тонка маржа","❌ збиток"))
A14: Зеплайн-піраміда | B14: id258 | C14: 451.12 | D14: 76 | E14: =IFERROR(C14/D14,0) | F14: =Економіка!$B$6-E14*Параметри!$B$10 | G14: =F14*D14 | H14: =IFERROR(G14/(C14*Параметри!$B$10),0) | I14: =IF(E14<=Економіка!$B$8,"✅ прибутковий",IF(E14<=Економіка!$B$7,"⚠️ тонка маржа","❌ збиток"))
A15: Разом | C15: =SUM(C4:C14) | D15: =SUM(D4:D14) | E15: =IFERROR(C15/D15,0) | G15: =SUM(G4:G14) | H15: =IFERROR(G15/(C15*Параметри!$B$10),0)
A17: Джерело: Meta Ads API, кампанії кабінетів «1 бм 2 рк (MAX)», «ХітМаркет», «рк2», 90 днів до 01.10.2026, ліди = подія Lead пікселя. Апрув і викуп усіх товарів = середні з «Параметри», доки не підключено LP-CRM по товарах.

Sheet Ваги
A1: Блоки Product Score і шкала 0–5
A3: Блок | B3: Вага | C3: 0–1 бал | D3: 2–3 бали | E3: 4–5 балів
A4: Тренд (Google Trends US/EU/UA) | B4: 20 | C4: Падає або плаский | D4: Стабільний або сезонний | E4: Росте у US 90 днів, в UA ще не піку
A5: Рекламний доказ (Ad Library US/EU) | B5: 20 | C5: Майже нема реклами | D5: Кілька рекламодавців, реклама < 30 днів | E5: Багато рекламодавців, реклама живе > 30 днів, нові креативи
A6: Насиченість UA (5 = вільна ніша) | B6: 15 | C6: Десятки конкурентів, демпінг | D6: Кілька конкурентів | E6: Майже немає в UA
A7: Юніт-економіка | B7: 20 | C7: Маржа < 200 ₴, крихкий/важкий | D7: Маржа 250–350 ₴ | E7: Маржа > 350 ₴ або легкий допродаж
A8: Відповідність ЦА 45+ | B8: 15 | C8: Молодіжний товар, складно показати | D8: Частково підходить | E8: Побут/кухня/город/здоров'я, «вау» на відео
A9: Схожість з вашими переможцями | B9: 10 | C9: Нова незнайома категорія | D9: Суміжна категорія | E9: Як подрібнювач/блендер/компресор
A10: Сума ваг (має бути 100) | B10: =SUM(B4:B9)
A12: Штраф за ризики: 0–20 балів (політики Meta щодо здоров'я, гарантійні повернення, розмірна сітка, кінець сезону).
A13: Пороги рішення
A14: «В тест» від Score | B14: 70
A15: «Спостерігати» від Score | B15: 55

Sheet Скоринг
A1: Скоринг кандидатів
A2: Сині клітинки заповнюєте ви (оцінки 0–5, штраф 0–20, очікуваний CPL). Score і рішення рахуються автоматично. Рядок 5 — приклад.
A4: Товар | B4: Тренд | C4: Реклама US/EU | D4: Насиченість UA | E4: Юніт-економіка | F4: ЦА 45+ | G4: Схожість | H4: Штраф ризиків | I4: Очік. CPL, $ | J4: Score | K4: Допустимий CPL, $ | L4: CPL-фільтр | M4: Рішення | N4: Коментар
A5: Електрична щітка-скрабер | B5: 4 | C5: 4 | D5: 3 | E5: 3 | F5: 5 | G5: 3 | H5: 0 | I5: 2.8 | J5: =IF(A5="","",ROUND((B5*Ваги!$B$4+C5*Ваги!$B$5+D5*Ваги!$B$6+E5*Ваги!$B$7+F5*Ваги!$B$8+G5*Ваги!$B$9)/5-H5,0)) | K5: =IF(A5="","",Економіка!$B$8) | L5: =IF(OR(A5="",I5=""),"",IF(I5<=Економіка!$B$8,"OK",IF(I5<=Економіка!$B$7,"Тонко","Дорого"))) | M5: =IF(A5="","",IF(L5="Дорого","Відкинути",IF(J5>=Ваги!$B$14,"В тест",IF(J5>=Ваги!$B$15,"Спостерігати","Відкинути")))) | N5: US: 92 активні оголошення; UA: ~95 (частина нерелевантні); біль «прибирання без нахилів»
A6: Бездротовий вакууматор | B6: 4 | C6: 4 | D6: 3 | E6: 3 | F6: 4 | G6: 3 | H6: 0 | I6: 3 | J6: =IF(A6="","",ROUND((B6*Ваги!$B$4+C6*Ваги!$B$5+D6*Ваги!$B$6+E6*Ваги!$B$7+F6*Ваги!$B$8+G6*Ваги!$B$9)/5-H6,0)) | K6: =IF(A6="","",Економіка!$B$8) | L6: =IF(OR(A6="",I6=""),"",IF(I6<=Економіка!$B$8,"OK",IF(I6<=Економіка!$B$7,"Тонко","Дорого"))) | M6: =IF(A6="","",IF(L6="Дорого","Відкинути",IF(J6>=Ваги!$B$14,"В тест",IF(J6>=Ваги!$B$15,"Спостерігати","Відкинути")))) | N6: US: 105 оголошень, тренд TikTok Shop; UA: ~115; ваш вакууматор мав CPL $4.4 (мала вибірка)
A7: Міні-подрібнювач часнику | B7: 3 | C7: 5 | D7: 2 | E7: 2 | F7: 4 | G7: 5 | H7: 5 | I7: 2 | J7: =IF(A7="","",ROUND((B7*Ваги!$B$4+C7*Ваги!$B$5+D7*Ваги!$B$6+E7*Ваги!$B$7+F7*Ваги!$B$8+G7*Ваги!$B$9)/5-H7,0)) | K7: =IF(A7="","",Економіка!$B$8) | L7: =IF(OR(A7="",I7=""),"",IF(I7<=Економіка!$B$8,"OK",IF(I7<=Економіка!$B$7,"Тонко","Дорого"))) | M7: =IF(A7="","",IF(L7="Дорого","Відкинути",IF(J7>=Ваги!$B$14,"В тест",IF(J7>=Ваги!$B$15,"Спостерігати","Відкинути")))) | N7: US: 556 оголошень, багато клонів; UA «подрібнювач»: ~169; низький чек — краще як допродаж
A8: Віброплатформа (нова хвиля) | B8: 2 | C8: 3 | D8: 2 | E8: 3 | F8: 3 | G8: 4 | H8: 5 | I8: 3.6 | J8: =IF(A8="","",ROUND((B8*Ваги!$B$4+C8*Ваги!$B$5+D8*Ваги!$B$6+E8*Ваги!$B$7+F8*Ваги!$B$8+G8*Ваги!$B$9)/5-H8,0)) | K8: =IF(A8="","",Економіка!$B$8) | L8: =IF(OR(A8="",I8=""),"",IF(I8<=Економіка!$B$8,"OK",IF(I8<=Економіка!$B$7,"Тонко","Дорого"))) | M8: =IF(A8="","",IF(L8="Дорого","Відкинути",IF(J8>=Ваги!$B$14,"В тест",IF(J8>=Ваги!$B$15,"Спостерігати","Відкинути")))) | N8: Мейнстрім у DE (Tchibo); ваш CPL нестабільний
A9: Red light therapy | B9: 3 | C9: 4 | D9: 3 | E9: 3 | F9: 3 | G9: 1 | H9: 15 | I9: 4.5 | J9: =IF(A9="","",ROUND((B9*Ваги!$B$4+C9*Ваги!$B$5+D9*Ваги!$B$6+E9*Ваги!$B$7+F9*Ваги!$B$8+G9*Ваги!$B$9)/5-H9,0)) | K9: =IF(A9="","",Економіка!$B$8) | L9: =IF(OR(A9="",I9=""),"",IF(I9<=Економіка!$B$8,"OK",IF(I9<=Економіка!$B$7,"Тонко","Дорого"))) | M9: =IF(A9="","",IF(L9="Дорого","Відкинути",IF(J9>=Ваги!$B$14,"В тест",IF(J9>=Ваги!$B$15,"Спостерігати","Відкинути")))) | N9: Ризик політик Meta щодо здоров'я
J10: =IF(A10="","",ROUND((B10*Ваги!$B$4+C10*Ваги!$B$5+D10*Ваги!$B$6+E10*Ваги!$B$7+F10*Ваги!$B$8+G10*Ваги!$B$9)/5-H10,0)) | K10: =IF(A10="","",Економіка!$B$8) | L10: =IF(OR(A10="",I10=""),"",IF(I10<=Економіка!$B$8,"OK",IF(I10<=Економіка!$B$7,"Тонко","Дорого"))) | M10: =IF(A10="","",IF(L10="Дорого","Відкинути",IF(J10>=Ваги!$B$14,"В тест",IF(J10>=Ваги!$B$15,"Спостерігати","Відкинути"))))
J11: =IF(A11="","",ROUND((B11*Ваги!$B$4+C11*Ваги!$B$5+D11*Ваги!$B$6+E11*Ваги!$B$7+F11*Ваги!$B$8+G11*Ваги!$B$9)/5-H11,0)) | K11: =IF(A11="","",Економіка!$B$8) | L11: =IF(OR(A11="",I11=""),"",IF(I11<=Економіка!$B$8,"OK",IF(I11<=Економіка!$B$7,"Тонко","Дорого"))) | M11: =IF(A11="","",IF(L11="Дорого","Відкинути",IF(J11>=Ваги!$B$14,"В тест",IF(J11>=Ваги!$B$15,"Спостерігати","Відкинути"))))
J12: =IF(A12="","",ROUND((B12*Ваги!$B$4+C12*Ваги!$B$5+D12*Ваги!$B$6+E12*Ваги!$B$7+F12*Ваги!$B$8+G12*Ваги!$B$9)/5-H12,0)) | K12: =IF(A12="","",Економіка!$B$8) | L12: =IF(OR(A12="",I12=""),"",IF(I12<=Економіка!$B$8,"OK",IF(I12<=Економіка!$B$7,"Тонко","Дорого"))) | M12: =IF(A12="","",IF(L12="Дорого","Відкинути",IF(J12>=Ваги!$B$14,"В тест",IF(J12>=Ваги!$B$15,"Спостерігати","Відкинути"))))
J13: =IF(A13="","",ROUND((B13*Ваги!$B$4+C13*Ваги!$B$5+D13*Ваги!$B$6+E13*Ваги!$B$7+F13*Ваги!$B$8+G13*Ваги!$B$9)/5-H13,0)) | K13: =IF(A13="","",Економіка!$B$8) | L13: =IF(OR(A13="",I13=""),"",IF(I13<=Економіка!$B$8,"OK",IF(I13<=Економіка!$B$7,"Тонко","Дорого"))) | M13: =IF(A13="","",IF(L13="Дорого","Відкинути",IF(J13>=Ваги!$B$14,"В тест",IF(J13>=Ваги!$B$15,"Спостерігати","Відкинути"))))
J14: =IF(A14="","",ROUND((B14*Ваги!$B$4+C14*Ваги!$B$5+D14*Ваги!$B$6+E14*Ваги!$B$7+F14*Ваги!$B$8+G14*Ваги!$B$9)/5-H14,0)) | K14: =IF(A14="","",Економіка!$B$8) | L14: =IF(OR(A14="",I14=""),"",IF(I14<=Економіка!$B$8,"OK",IF(I14<=Економіка!$B$7,"Тонко","Дорого"))) | M14: =IF(A14="","",IF(L14="Дорого","Відкинути",IF(J14>=Ваги!$B$14,"В тест",IF(J14>=Ваги!$B$15,"Спостерігати","Відкинути"))))
J15: =IF(A15="","",ROUND((B15*Ваги!$B$4+C15*Ваги!$B$5+D15*Ваги!$B$6+E15*Ваги!$B$7+F15*Ваги!$B$8+G15*Ваги!$B$9)/5-H15,0)) | K15: =IF(A15="","",Економіка!$B$8) | L15: =IF(OR(A15="",I15=""),"",IF(I15<=Економіка!$B$8,"OK",IF(I15<=Економіка!$B$7,"Тонко","Дорого"))) | M15: =IF(A15="","",IF(L15="Дорого","Відкинути",IF(J15>=Ваги!$B$14,"В тест",IF(J15>=Ваги!$B$15,"Спостерігати","Відкинути"))))
J16: =IF(A16="","",ROUND((B16*Ваги!$B$4+C16*Ваги!$B$5+D16*Ваги!$B$6+E16*Ваги!$B$7+F16*Ваги!$B$8+G16*Ваги!$B$9)/5-H16,0)) | K16: =IF(A16="","",Економіка!$B$8) | L16: =IF(OR(A16="",I16=""),"",IF(I16<=Економіка!$B$8,"OK",IF(I16<=Економіка!$B$7,"Тонко","Дорого"))) | M16: =IF(A16="","",IF(L16="Дорого","Відкинути",IF(J16>=Ваги!$B$14,"В тест",IF(J16>=Ваги!$B$15,"Спостерігати","Відкинути"))))
J17: =IF(A17="","",ROUND((B17*Ваги!$B$4+C17*Ваги!$B$5+D17*Ваги!$B$6+E17*Ваги!$B$7+F17*Ваги!$B$8+G17*Ваги!$B$9)/5-H17,0)) | K17: =IF(A17="","",Економіка!$B$8) | L17: =IF(OR(A17="",I17=""),"",IF(I17<=Економіка!$B$8,"OK",IF(I17<=Економіка!$B$7,"Тонко","Дорого"))) | M17: =IF(A17="","",IF(L17="Дорого","Відкинути",IF(J17>=Ваги!$B$14,"В тест",IF(J17>=Ваги!$B$15,"Спостерігати","Відкинути"))))
J18: =IF(A18="","",ROUND((B18*Ваги!$B$4+C18*Ваги!$B$5+D18*Ваги!$B$6+E18*Ваги!$B$7+F18*Ваги!$B$8+G18*Ваги!$B$9)/5-H18,0)) | K18: =IF(A18="","",Економіка!$B$8) | L18: =IF(OR(A18="",I18=""),"",IF(I18<=Економіка!$B$8,"OK",IF(I18<=Економіка!$B$7,"Тонко","Дорого"))) | M18: =IF(A18="","",IF(L18="Дорого","Відкинути",IF(J18>=Ваги!$B$14,"В тест",IF(J18>=Ваги!$B$15,"Спостерігати","Відкинути"))))
J19: =IF(A19="","",ROUND((B19*Ваги!$B$4+C19*Ваги!$B$5+D19*Ваги!$B$6+E19*Ваги!$B$7+F19*Ваги!$B$8+G19*Ваги!$B$9)/5-H19,0)) | K19: =IF(A19="","",Економіка!$B$8) | L19: =IF(OR(A19="",I19=""),"",IF(I19<=Економіка!$B$8,"OK",IF(I19<=Економіка!$B$7,"Тонко","Дорого"))) | M19: =IF(A19="","",IF(L19="Дорого","Відкинути",IF(J19>=Ваги!$B$14,"В тест",IF(J19>=Ваги!$B$15,"Спостерігати","Відкинути"))))

Sheet Протокол тесту
A1: Протокол тесту товару
A3: Етап | B3: Значення | C3: Правило
A4: Бюджет тесту, $/день | B4: =Параметри!B12 | C4: OUTCOME_LEADS, широка аудиторія UA, 3–4 відео-креативи
A5: Загальний бюджет тесту, $ | B5: =Параметри!B12*Параметри!B13 | C5: на один товар
A6: Kill-точка: спенд, $ | B6: =Параметри!B16*Економіка!B8 | C6: після цього спенду перевіряємо CPL
A7: Kill, якщо CPL вищий за, $ | B7: =Економіка!B7 | C7: беззбитковий CPL → стоп
A8: Scale, якщо CPL не вищий за, $ | B8: =Економіка!B8 | C8: і апрув у LP-CRM ≥ мінімального
A9: Мінімальний апрув для scale | B9: =Параметри!B15
A10: Бюджет scale, $/день | B10: =Параметри!B14 | C10: потім дублі в інші кабінети
A11: Між kill і scale | C11: CPL між цільовим і беззбитковим → тест нових креативів/оферу ще на 2 дні
A12: Фінальне рішення | C12: за ціною викупленого замовлення з LP-CRM через 10–14 днів
